ckanext/__init__.py
ckanext/create_typed_package/__init__.py
ckanext/create_typed_package/config.py
ckanext/create_typed_package/config_declaration.yaml
ckanext/create_typed_package/helpers.py
ckanext/create_typed_package/plugin.py
ckanext/create_typed_package/views.py
ckanext/create_typed_package/assets/resource.config
ckanext/create_typed_package/assets/webassets.yml
ckanext/create_typed_package/assets/scripts/package-type-selector.js
ckanext/create_typed_package/logic/__init__.py
ckanext/create_typed_package/logic/action.py
ckanext/create_typed_package/logic/auth.py
ckanext/create_typed_package/templates/page.html
ckanext/create_typed_package/templates/create_typed_package/snippets/asset.html
ckanext/create_typed_package/templates/package/ctp_select_dataset_type.html
ckanext/create_typed_package/templates/package/snippets/ctp_select_dataset_type_form.html
ckanext/create_typed_package/templates/snippets/add_dataset.html
ckanext/create_typed_package/tests/__init__.py
ckanext/create_typed_package/tests/test_plugin.py
ckanext/create_typed_package/tests/test_view.py
ckanext/create_typed_package/tests/logic/test_action.py
ckanext/create_typed_package/tests/logic/test_auth.py
ckanext/create_typed_package/tests/schemas/first.yaml
ckanext/create_typed_package/tests/schemas/second.yaml
ckanext/create_typed_package/tests/schemas/third.yaml
ckanext_create_typed_package-0.5.2.dist-info/METADATA
ckanext_create_typed_package-0.5.2.dist-info/WHEEL
ckanext_create_typed_package-0.5.2.dist-info/entry_points.txt
ckanext_create_typed_package-0.5.2.dist-info/top_level.txt
ckanext_create_typed_package-0.5.2.dist-info/RECORD
